<?xml version="1.0" encoding="utf-8"?>
<edmx:Edmx Version="1.0" xmlns:edmx="http://schemas.microsoft.com/ado/2007/06/edmx" xmlns:m="http://schemas.microsoft.com/ado/2007/08/dataservices/metadata" xmlns:sap="http://www.sap.com/Protocols/SAPData">
    <edmx:Reference Uri=".1/sap/opu/odata/IWFND/CATALOGSERVICE;v=2/Vocabularies(TechnicalName='%2FIWBEP%2FVOC_COMMON',Version='0001',SAP__Origin='LOCAL')/$value" xmlns:edmx="http://docs.oasis-open.org/odata/ns/edmx">
        <edmx:Include Namespace="com.sap.vocabularies.Common.v1" Alias="Common"/>
    </edmx:Reference>
    <edmx:Reference Uri=".1/sap/opu/odata/IWFND/CATALOGSERVICE;v=2/Vocabularies(TechnicalName='%2FIWBEP%2FVOC_CAPABILITIES',Version='0001',SAP__Origin='LOCAL')/$value" xmlns:edmx="http://docs.oasis-open.org/odata/ns/edmx">
        <edmx:Include Namespace="Org.OData.Capabilities.V1" Alias="Capabilities"/>
    </edmx:Reference>
    <edmx:Reference Uri=".1/sap/opu/odata/IWFND/CATALOGSERVICE;v=2/Vocabularies(TechnicalName='%2FIWBEP%2FVOC_COMMUNICATION',Version='0001',SAP__Origin='LOCAL')/$value" xmlns:edmx="http://docs.oasis-open.org/odata/ns/edmx">
        <edmx:Include Namespace="com.sap.vocabularies.Communication.v1" Alias="Communication"/>
    </edmx:Reference>
    <edmx:Reference Uri=".1/sap/opu/odata/IWFND/CATALOGSERVICE;v=2/Vocabularies(TechnicalName='%2FIWBEP%2FVOC_AGGREGATION',Version='0001',SAP__Origin='LOCAL')/$value" xmlns:edmx="http://docs.oasis-open.org/odata/ns/edmx">
        <edmx:Include Namespace="Org.OData.Aggregation.V1" Alias="Aggregation"/>
    </edmx:Reference>
    <edmx:Reference Uri=".1/sap/opu/odata/IWFND/CATALOGSERVICE;v=2/Vocabularies(TechnicalName='%2FIWBEP%2FVOC_PERSONALDATA',Version='0001',SAP__Origin='LOCAL')/$value" xmlns:edmx="http://docs.oasis-open.org/odata/ns/edmx">
        <edmx:Include Namespace="com.sap.vocabularies.PersonalData.v1" Alias="PersonalData"/>
    </edmx:Reference>
    <edmx:DataServices m:DataServiceVersion="2.0">
        <Schema Namespace="ZSCHD_E07_00_CDS" xml:lang="en" sap:schema-version="1" xmlns="http://schemas.microsoft.com/ado/2008/09/edm">
            <EntityType Name="ZSCHD_E07_00Type" sap:label="TEST" sap:content-version="1">
                <Key>
                    <PropertyRef Name="Prdonum"/>
                </Key>
                <Property Name="Prdonum" Type="Edm.String" Nullable="false" MaxLength="10" sap:display-format="UpperCase" sap:label="문서번호"/>
                <Property Name="Wctxt" Type="Edm.String" MaxLength="60" sap:display-format="UpperCase" sap:label="작업장명"/>
                <Property Name="Schdate" Type="Edm.DateTime" Precision="0" sap:display-format="Date" sap:label="Date"/>
                <Property Name="Stime" Type="Edm.Time" Precision="0"/>
                <Property Name="Etime" Type="Edm.Time" Precision="0"/>
                <Property Name="Itemnum" Type="Edm.String" MaxLength="3" sap:display-format="NonNegative" sap:label="순번"/>
                <Property Name="Sschtype" Type="Edm.String" MaxLength="2" sap:display-format="UpperCase" sap:label="스케쥴타입"/>
                <Property Name="Eschtype" Type="Edm.String" MaxLength="2" sap:display-format="UpperCase" sap:label="스케쥴타입"/>
            </EntityType>
            <EntityContainer Name="ZSCHD_E07_00_CDS_Entities" m:IsDefaultEntityContainer="true" sap:message-scope-supported="true" sap:supported-formats="atom json xlsx">
                <EntitySet Name="ZSCHD_E07_00" EntityType="ZSCHD_E07_00_CDS.ZSCHD_E07_00Type" sap:creatable="false" sap:updatable="false" sap:deletable="false" sap:content-version="1"/>
            </EntityContainer>
            <Annotations Target="ZSCHD_E07_00_CDS.ZSCHD_E07_00_CDS_Entities" xmlns="http://docs.oasis-open.org/odata/ns/edm">
                <Annotation Term="Aggregation.ApplySupported">
                    <Record>
                        <PropertyValue Property="Transformations">
                            <Collection>
                                <String>aggregate</String>
                                <String>groupby</String>
                                <String>filter</String>
                            </Collection>
                        </PropertyValue>
                        <PropertyValue Property="Rollup" EnumMember="None"/>
                    </Record>
                </Annotation>
            </Annotations>
            <atom:link rel="self" href="http://edu.bgis.co.kr:8001/sap/opu/odata/sap/ZSCHD_E07_00_CDS/$metadata" xmlns:atom="http://www.w3.org/2005/Atom"/>
            <atom:link rel="latest-version" href="http://edu.bgis.co.kr:8001/sap/opu/odata/sap/ZSCHD_E07_00_CDS/$metadata" xmlns:atom="http://www.w3.org/2005/Atom"/>
        </Schema>
    </edmx:DataServices>
</edmx:Edmx>